pygametext/__init__.py
pygametext-0.1.0.4.dist-info/LICENSE
pygametext-0.1.0.4.dist-info/METADATA
pygametext-0.1.0.4.dist-info/WHEEL
pygametext-0.1.0.4.dist-info/top_level.txt
pygametext-0.1.0.4.dist-info/RECORD
