Metadata-Version: 2.1
Name: pygametext
Version: 0.1.0.4
Summary: This Package adds UI Elements like Buttons and Textboxes to PyGame.
Home-page: https://github.com/LeBogoo/pygametext
Author: LeBogo
Author-email: lebogomc@gmail.com
License: UNKNOWN
Platform: UNKNOWN
Classifier: Programming Language :: Python :: 3
Classifier: License :: OSI Approved :: MIT License
Classifier: Operating System :: OS Independent
Requires-Python: >=3.6
